Metrics/__init__.py
Metrics/metrics.py
confusion_metrics-0.1.0.dist-info/DESCRIPTION.rst
confusion_metrics-0.1.0.dist-info/METADATA
confusion_metrics-0.1.0.dist-info/RECORD
confusion_metrics-0.1.0.dist-info/WHEEL
confusion_metrics-0.1.0.dist-info/metadata.json
confusion_metrics-0.1.0.dist-info/top_level.txt
