Metadata-Version: 2.0
Name: confusion-metrics
Version: 0.1.0
Summary: A collection of metrics for analysing confusion matrices
Home-page: https://bitbucket.org/davidmam/metrics.git
Author: Dr David Martin
Author-email: d.m.a.martin@dundee.ac.uk
License: UNKNOWN
Platform: UNKNOWN
Classifier: Programming Language :: Python :: 3
Classifier: License :: OSI Approved :: MIT License
Classifier: Operating System :: OS Independent
Requires-Python: >=3.0
